utm_tracker_django/__init__.py
utm_tracker_django/conf.py
utm_tracker_django/middleware.py
utm_tracker_django-1.1.1.dist-info/licenses/LICENSE
utm_tracker_django-1.1.1.dist-info/METADATA
utm_tracker_django-1.1.1.dist-info/WHEEL
utm_tracker_django-1.1.1.dist-info/top_level.txt
utm_tracker_django-1.1.1.dist-info/RECORD
