Metadata-Version: 2.4
Name: utm-tracker-django
Version: 1.1.1
Summary: Middleware to track UTM parameters in Django
Home-page: https://github.com/Weird-Labs-Pvt-Ltd/utm-tracker-django
Author: Preet Sonpal
Author-email: preet@weirdlabs.in
Classifier: Framework :: Django
Classifier: Programming Language :: Python :: 3
Classifier: License :: OSI Approved :: MIT License
License-File: LICENSE
Dynamic: author
Dynamic: author-email
Dynamic: classifier
Dynamic: description
Dynamic: description-content-type
Dynamic: home-page
Dynamic: license-file
Dynamic: summary
